clocky/__init__.py
clocky/__main__.py
clocky/test_clocky.py
clocky-0.0.7.dist-info/LICENSE.txt
clocky-0.0.7.dist-info/METADATA
clocky-0.0.7.dist-info/WHEEL
clocky-0.0.7.dist-info/entry_points.txt
clocky-0.0.7.dist-info/top_level.txt
clocky-0.0.7.dist-info/RECORD
