Metadata-Version: 2.1
Name: clocky
Version: 0.0.7
Home-page: http://github.com/csm10495/clocky
Author: csm10495
Author-email: csm10495@gmail.com
License: MIT License
Classifier: Intended Audience :: Developers
Classifier: Natural Language :: English
Classifier: Operating System :: POSIX
Classifier: Operating System :: Microsoft :: Windows
Classifier: Programming Language :: Python
Classifier: Programming Language :: Python :: 3
Requires-Python: >=3.8
License-File: LICENSE.txt
Requires-Dist: psutil
